int_connector_lib/__init__.py
int_connector_lib/broker.py
int_connector_lib/config.py
int_connector_lib/health.py
int_connector_lib/manager.py
int_connector_lib/proto/__init__.py
int_connector_lib/proto/grpc_broker_pb2.py
int_connector_lib/proto/grpc_broker_pb2_grpc.py
int_connector_lib/proto/grpc_controller_pb2.py
int_connector_lib/proto/grpc_controller_pb2_grpc.py
int_connector_lib/proto/grpc_stdio_pb2.py
int_connector_lib/proto/grpc_stdio_pb2_grpc.py
int_connector_lib/proto/manager_pb2.py
int_connector_lib/proto/manager_pb2_grpc.py
int_connector_lib/proto/source_pb2.py
int_connector_lib/proto/source_pb2_grpc.py
int_connector_lib/protobuf.py
int_connector_lib/server.py
int_connector_lib/source.py
int_connector_lib-0.1.0.dist-info/METADATA
int_connector_lib-0.1.0.dist-info/WHEEL
int_connector_lib-0.1.0.dist-info/RECORD
