Metadata-Version: 2.1
Name: int_connector_lib
Version: 0.1.0
Summary: Description
License: closed
Requires-Python: >=3.11,<3.12
Classifier: License :: Other/Proprietary License
Classifier: Programming Language :: Python :: 3
Classifier: Programming Language :: Python :: 3.11
Requires-Dist: grpcio (>=1.60.1,<2.0.0)
Requires-Dist: grpcio-health-checking (>=1.60.1,<2.0.0)
Requires-Dist: pydantic (>=2.6.1,<3.0.0)
